_version.py
config.py
main.py
models.py
middleware/__init__.py
middleware/error_handler.py
middleware/logging_middleware.py
middleware/metrics_middleware.py
ollama_openai_proxy-0.6.5.dist-info/licenses/LICENSE
routers/__init__.py
routers/chat.py
routers/embeddings.py
routers/metrics.py
routers/models.py
routers/version.py
translators/__init__.py
translators/base.py
translators/chat.py
translators/embeddings.py
utils/__init__.py
utils/benchmarks.py
utils/exceptions.py
utils/http_client.py
utils/load_test.py
utils/logging.py
utils/metrics.py
utils/request_body.py
ollama_openai_proxy-0.6.5.dist-info/METADATA
ollama_openai_proxy-0.6.5.dist-info/WHEEL
ollama_openai_proxy-0.6.5.dist-info/entry_points.txt
ollama_openai_proxy-0.6.5.dist-info/top_level.txt
ollama_openai_proxy-0.6.5.dist-info/RECORD
