Metadata-Version: 2.4
Name: ollama-openai-proxy
Version: 0.6.5
Summary: A proxy service that translates Ollama API requests to OpenAI-compatible backends
Author-email: Development Team <dev@example.com>
License: MIT
Project-URL: Homepage, https://github.com/eyalrot/ollama_openai
Project-URL: Bug Reports, https://github.com/eyalrot/ollama_openai/issues
Project-URL: Source, https://github.com/eyalrot/ollama_openai
Project-URL: Documentation, https://github.com/eyalrot/ollama_openai#readme
Keywords: ollama,openai,proxy,api,translation
Classifier: Development Status :: 5 - Production/Stable
Classifier: Intended Audience :: Developers
Classifier: License :: OSI Approved :: MIT License
Classifier: Operating System :: OS Independent
Classifier: Programming Language :: Python :: 3
Classifier: Programming Language :: Python :: 3.9
Classifier: Programming Language :: Python :: 3.10
Classifier: Programming Language :: Python :: 3.11
Classifier: Programming Language :: Python :: 3.12
Classifier: Topic :: Internet :: WWW/HTTP :: HTTP Servers
Classifier: Topic :: Software Development :: Libraries :: Python Modules
Requires-Python: >=3.9
License-File: LICENSE
Requires-Dist: fastapi>=0.104.0
Requires-Dist: uvicorn[standard]>=0.24.0
Requires-Dist: pydantic>=2.5.0
Requires-Dist: pydantic-settings>=2.1.0
Requires-Dist: httpx>=0.25.0
Requires-Dist: structlog>=23.2.0
Requires-Dist: python-multipart>=0.0.6
Requires-Dist: psutil>=5.9.0
Requires-Dist: python-dotenv>=1.0.0
Requires-Dist: aiofiles>=23.2.0
Provides-Extra: dev
Requires-Dist: pytest>=7.4.0; extra == "dev"
Requires-Dist: pytest-asyncio>=0.21.0; extra == "dev"
Requires-Dist: pytest-cov>=4.1.0; extra == "dev"
Requires-Dist: pytest-mock>=3.12.0; extra == "dev"
Requires-Dist: black>=23.0.0; extra == "dev"
Requires-Dist: ruff>=0.1.0; extra == "dev"
Requires-Dist: mypy>=1.7.0; extra == "dev"
Requires-Dist: httpx-mock>=0.10.0; extra == "dev"
Requires-Dist: memory-profiler>=0.61.0; extra == "dev"
Requires-Dist: psutil>=5.9.0; extra == "dev"
Dynamic: license-file
